caqtus_devices/imaging_source/__init__.py
caqtus_devices/imaging_source/_compiler.py
caqtus_devices/imaging_source/_extension.py
caqtus_devices/imaging_source/py.typed
caqtus_devices/imaging_source/configuration/__init__.py
caqtus_devices/imaging_source/configuration/configuration.py
caqtus_devices/imaging_source/configuration_editor/__init__.py
caqtus_devices/imaging_source/configuration_editor/editor.py
caqtus_devices/imaging_source/runtime/__init__.py
caqtus_devices/imaging_source/runtime/imaging_source_camera.py
caqtus_devices/imaging_source/runtime/tisgrabber/__init__.py
caqtus_devices/imaging_source/runtime/tisgrabber/tisgrabber.py
caqtus_devices_imaging_source-1.10.0.dist-info/METADATA
caqtus_devices_imaging_source-1.10.0.dist-info/WHEEL
caqtus_devices_imaging_source-1.10.0.dist-info/RECORD
