Metadata-Version: 2.4
Name: caqtus-devices-imaging-source
Version: 1.10.0
Summary: Add your description here
Author-email: light-scattering-io <lecaqtus66@gmail.com>
Requires-Python: >=3.12
Requires-Dist: caqtus-suite>=6.18.1
Requires-Dist: pyside6!=6.8.1.1,>=6.8.1
